classify/__init__.py
classify/clipclassifier.py
classify/main.py
classify/thumbnail.py
classify/trackprediction.py
config/__init__.py
config/buildconfig.py
config/classifyconfig.py
config/config.py
config/defaultconfig.py
config/locationconfig.py
config/test_timewindow.py
config/thermalconfig.py
config/timewindow.py
config/trackingconfig.py
config/trackingmotionconfig.py
config/trainconfig.py
ml_tools/__init__.py
ml_tools/dataset.py
ml_tools/datasetstructures.py
ml_tools/featurenorms.py
ml_tools/forestmodel.py
ml_tools/frame.py
ml_tools/framecache.py
ml_tools/globals.py
ml_tools/hyperparams.py
ml_tools/imageprocessing.py
ml_tools/interpreter.py
ml_tools/irdataset.py
ml_tools/irwriter.py
ml_tools/kerasmodel.py
ml_tools/logs.py
ml_tools/mpeg_creator.py
ml_tools/openvinoclassify.py
ml_tools/preprocess.py
ml_tools/preprocessresnet.py
ml_tools/previewer.py
ml_tools/rawdb.py
ml_tools/rectangle.py
ml_tools/test_rectangle.py
ml_tools/tfdataset.py
ml_tools/tfrecord_util.py
ml_tools/tfwriter.py
ml_tools/thermaldataset.py
ml_tools/thermalwriter.py
ml_tools/tools.py
ml_tools/trackdatabase.py
ml_tools/visualise.py
ml_tools/resnet/resnet.py
ml_tools/resnet/wr_resnet.py
piclassifier/__init__.py
piclassifier/attiny.py
piclassifier/beacon.py
piclassifier/classifier.service
piclassifier/cptvmotiondetector.py
piclassifier/cptvrecorder.py
piclassifier/cptvtest.py
piclassifier/dbuslistener.py
piclassifier/dummyrecorder.py
piclassifier/eventreporter.py
piclassifier/headerinfo.py
piclassifier/irmotiondetector.py
piclassifier/irrecorder.py
piclassifier/monitorconfig.py
piclassifier/motiondetector.py
piclassifier/piclassifier.py
piclassifier/piclassify.py
piclassifier/postprocess.py
piclassifier/processor.py
piclassifier/recorder.py
piclassifier/run-classifier.sh
piclassifier/servemodel.py
piclassifier/service.py
piclassifier/telemetry.py
piclassifier/throttledrecorder.py
piclassifier/trapcontroller.py
piclassifier/utils.py
piclassifier/cameras/__init__.py
piclassifier/cameras/boson.py
classifier_pipeline-0.0.44.dist-info/METADATA
classifier_pipeline-0.0.44.dist-info/WHEEL
classifier_pipeline-0.0.44.dist-info/entry_points.txt
classifier_pipeline-0.0.44.dist-info/licenses/LICENSE
classifier_pipeline-0.0.44.dist-info/RECORD
